a_pandas_ex_set/README.MD
a_pandas_ex_set/__init__.py
a_pandas_ex_set/requirements.txt
a_pandas_ex_set/thirdparty.json
a_pandas_ex_set-0.10.dist-info/LICENSE.rst
a_pandas_ex_set-0.10.dist-info/METADATA
a_pandas_ex_set-0.10.dist-info/WHEEL
a_pandas_ex_set-0.10.dist-info/top_level.txt
a_pandas_ex_set-0.10.dist-info/RECORD
